napari_spfluo/__init__.py
napari_spfluo/_sample_data.py
napari_spfluo/_utils_widgets.py
napari_spfluo/_version.py
napari_spfluo/ab_initio_widget.py
napari_spfluo/dbscan_widget.py
napari_spfluo/manual_ab_initio_widget.py
napari_spfluo/napari.yaml
napari_spfluo/rotate_widget.py
napari_spfluo/separate_widget.py
napari_spfluo/symmetrize_widget.py
napari_spfluo/_tests/__init__.py
napari_spfluo/_tests/test_sample_data.py
napari_spfluo/_tests/test_widget.py
napari_spfluo-0.1.0.dist-info/METADATA
napari_spfluo-0.1.0.dist-info/WHEEL
napari_spfluo-0.1.0.dist-info/entry_points.txt
napari_spfluo-0.1.0.dist-info/licenses/LICENSE
napari_spfluo-0.1.0.dist-info/RECORD
