Metadata-Version: 2.3
Name: napari-spfluo
Version: 0.1.0
Summary: A plugin to use spfluo within napari
Project-URL: Bug Tracker, https://github.com/jplumail/napari-spfluo/issues
Project-URL: Documentation, https://github.com/jplumail/napari-spfluo#README.md
Project-URL: Homepage, https://github.com/jplumail/napari-spfluo
Project-URL: Source Code, https://github.com/jplumail/napari-spfluo
Project-URL: User Support, https://github.com/jplumail/napari-spfluo/issues
Author-email: Jean Plumail <jplumail@unistra.fr>
License: MIT
Classifier: Development Status :: 2 - Pre-Alpha
Classifier: Framework :: napari
Classifier: Intended Audience :: Developers
Classifier: License :: OSI Approved :: MIT License
Classifier: Operating System :: OS Independent
Classifier: Programming Language :: Python
Classifier: Programming Language :: Python :: 3
Classifier: Programming Language :: Python :: 3 :: Only
Classifier: Programming Language :: Python :: 3.8
Classifier: Programming Language :: Python :: 3.9
Classifier: Programming Language :: Python :: 3.10
Classifier: Programming Language :: Python :: 3.11
Classifier: Topic :: Scientific/Engineering :: Image Processing
Requires-Python: >=3.8
Requires-Dist: magicgui
Requires-Dist: numpy
Requires-Dist: qtpy
Requires-Dist: scikit-image
Requires-Dist: spfluo[ab-initio-reconstruction]
